LICENSE
MANIFEST.in
README.md
requirements.txt
setup.py
gpt_computer_agent/__init__.py
gpt_computer_agent/agentic.py
gpt_computer_agent/api.py
gpt_computer_agent/character.py
gpt_computer_agent/custom_callback.py
gpt_computer_agent/display_tools.py
gpt_computer_agent/gpt_computer_agent.py
gpt_computer_agent/llm.py
gpt_computer_agent/llm_settings.py
gpt_computer_agent/remote.py
gpt_computer_agent/standard_tools.py
gpt_computer_agent/start.py
gpt_computer_agent/teams.py
gpt_computer_agent/tooler.py
gpt_computer_agent/top_bar_wrapper.py
gpt_computer_agent.egg-info/PKG-INFO
gpt_computer_agent.egg-info/SOURCES.txt
gpt_computer_agent.egg-info/dependency_links.txt
gpt_computer_agent.egg-info/entry_points.txt
gpt_computer_agent.egg-info/not-zip-safe
gpt_computer_agent.egg-info/requires.txt
gpt_computer_agent.egg-info/top_level.txt
gpt_computer_agent/agent/__init__.py
gpt_computer_agent/agent/agent.py
gpt_computer_agent/agent/agent_tools.py
gpt_computer_agent/agent/assistant.py
gpt_computer_agent/agent/background.py
gpt_computer_agent/agent/chat_history.py
gpt_computer_agent/agent/process.py
gpt_computer_agent/audio/__init__.py
gpt_computer_agent/audio/record.py
gpt_computer_agent/audio/stt.py
gpt_computer_agent/audio/tts.py
gpt_computer_agent/audio/wake_word.py
gpt_computer_agent/gui/__init__.py
gpt_computer_agent/gui/button.py
gpt_computer_agent/gui/llmsettings.py
gpt_computer_agent/gui/settings.py
gpt_computer_agent/gui/signal.py
gpt_computer_agent/screen/__init__.py
gpt_computer_agent/screen/shot.py
gpt_computer_agent/utils/db.py
gpt_computer_agent/utils/telemetry.py
gpt_computer_agent/utils/media/SF-Pro-Text-Bold.otf
gpt_computer_agent/utils/media/icon.ico