Metadata-Version: 2.1
Name: gpt-computer-agent
Version: 1.0.2
Summary: GPT
Home-page: https://github.com/khulnasoft/gpt-computer-agent
Author: KhulnaSoft DevOps
Author-email: info@khulnasoft.com
License: MIT
Platform: UNKNOWN
Requires-Python: >= 3.9
Provides-Extra: base
Provides-Extra: default
Provides-Extra: agentic
Provides-Extra: wakeword
Provides-Extra: api
Provides-Extra: local_tts
